mdo_engine/__init__.py
mdo_engine/boundary/__init__.py
mdo_engine/boundary/data.py
mdo_engine/boundary/interface.py
mdo_engine/control/__init__.py
mdo_engine/control/data.py
mdo_engine/control/factory.py
mdo_engine/control/pipeline.py
mdo_engine/control/simulation.py
mdo_engine/control/sockets.py
mdo_engine/entity/__init__.py
mdo_engine/entity/data.py
mdo_engine/entity/pipeline.py
mdo_engine/entity/simulation.py
mdo_engine/test/__init__.py
mdo_engine/test/data/__init__.py
mdo_engine/test/data/definitions.py
mdo_engine/test/data/yaml/wave.yaml
mdo_engine/test/interfaces/__init__.py
mdo_engine/test/interfaces/sptfile.py
mdo_engine/test/modules/__init__.py
mdo_engine/test/modules/datawell.py
mdo_engine/utilities/__init__.py
mdo_engine/utilities/analysis.py
mdo_engine/utilities/data.py
mdo_engine/utilities/database.py
mdo_engine/utilities/files.py
mdo_engine/utilities/identity.py
mdo_engine/utilities/misc.py
mdo_engine/utilities/plugins.py
mdo_engine-1.0.0.dist-info/entry_points.txt
mdo_engine-1.0.0.dist-info/LICENSE.txt
mdo_engine-1.0.0.dist-info/METADATA
mdo_engine-1.0.0.dist-info/WHEEL
mdo_engine-1.0.0.dist-info/RECORD
