Metadata-Version: 2.1
Name: mdo-engine
Version: 1.0.0
Summary: Data management, coupling and execution for MDO problems
License: MIT
Author: Mathew Topper
Author-email: damm_horse@yahoo.co.uk
Requires-Python: >=3.13,<4.0
Classifier: License :: OSI Approved :: MIT License
Classifier: Programming Language :: Python :: 3
Classifier: Programming Language :: Python :: 3.13
Requires-Dist: numpy (>=2.1.3,<3.0.0)
Requires-Dist: openpyxl (>=3.1.5,<4.0.0)
Requires-Dist: pandas (>=2.2.3,<3.0.0)
Requires-Dist: polite-config (>=1.0.0,<2.0.0)
Requires-Dist: python-box (>=7.2.0,<8.0.0)
Requires-Dist: pywin32 (>=308,<309) ; sys_platform == "win32"
Requires-Dist: pyyaml (>=6.0.2,<7.0.0)
Requires-Dist: sqlalchemy (>=2.0.36,<3.0.0)
Requires-Dist: xlrd (>=2.0.1,<3.0.0)
Requires-Dist: xlwt (>=1.3.0,<2.0.0)
